wordflux/__init__.py
wordflux/docxtranslator.py
wordflux/document/document.py
wordflux/utils/decorator.py
wordflux/utils/is_numeric.py
wordflux/utils/openai_client.py
wordflux/utils/prompt_builder.py
wordflux/utils/spinner.py
wordflux/worker/extractor.py
wordflux/worker/injector.py
wordflux/worker/translator.py
wordflux-0.1.0.dist-info/METADATA
wordflux-0.1.0.dist-info/WHEEL
wordflux-0.1.0.dist-info/entry_points.txt
wordflux-0.1.0.dist-info/RECORD
