Metadata-Version: 2.4
Name: wordflux
Version: 0.1.0
Summary: Translate DOCX files while preserving formatting.
Project-URL: Homepage, https://github.com/pnnbao97/wordflux
Project-URL: Repository, https://github.com/pnnbao97/wordflux
Project-URL: Issues, https://github.com/pnnbao97/wordflux/issues
Author-email: Pham Nguyen Ngoc Bao <pnnbao@gmail.com>
License: MIT
Requires-Python: >=3.12
Requires-Dist: openai>=2.3.0
Requires-Dist: python-docx>=1.2.0
Requires-Dist: pyyaml>=6.0.3
Requires-Dist: tqdm>=4.67.1
